lribeiro.cherrypy.authorizer-1.0.2-py3.4-nspkg.pth
lribeiro/cherrypy/authorizer/__init__.py
lribeiro/cherrypy/authorizer/_constants.py
lribeiro/cherrypy/authorizer/exceptions.py
lribeiro/cherrypy/authorizer/utils.py
lribeiro/cherrypy/authorizer/authentication.py
lribeiro/cherrypy/authorizer/authorization.py
lribeiro.cherrypy.authorizer-1.0.2.dist-info/WHEEL
lribeiro.cherrypy.authorizer-1.0.2.dist-info/top_level.txt
lribeiro.cherrypy.authorizer-1.0.2.dist-info/DESCRIPTION.rst
lribeiro.cherrypy.authorizer-1.0.2.dist-info/namespace_packages.txt
lribeiro.cherrypy.authorizer-1.0.2.dist-info/METADATA
lribeiro.cherrypy.authorizer-1.0.2.dist-info/metadata.json
lribeiro.cherrypy.authorizer-1.0.2.dist-info/RECORD
