Metadata-Version: 2.0
Name: lribeiro.cherrypy.authorizer
Version: 1.0.2
Summary: Extensible session based authentication and claims based authorization tool for CherryPy
Home-page: http://bitbucket.org/livioribeiro/cherrypy-authorizer
Author: Livio Ribeiro
Author-email: livioribeiro@outlook.com
License: BSD License
Keywords: authentication,authorization,access control,cherrypy
Platform: UNKNOWN
Classifier: Development Status :: 4 - Beta
Classifier: Environment :: Web Environment
Classifier: Framework :: CherryPy
Classifier: Intended Audience :: Developers
Classifier: License :: OSI Approved :: BSD License
Classifier: Operating System :: OS Independent
Classifier: Programming Language :: Python
Classifier: Programming Language :: Python :: 2
Classifier: Programming Language :: Python :: 2.7
Classifier: Programming Language :: Python :: 3
Classifier: Programming Language :: Python :: Implementation :: PyPy
Classifier: Topic :: Internet :: WWW/HTTP
Classifier: Topic :: Internet :: WWW/HTTP :: Dynamic Content
Classifier: Topic :: Internet :: WWW/HTTP :: Session
Requires-Dist: CherryPy
